b3u/__init__.py
b3u/b3u.py
b3u-2.0.0.dist-info/LICENSE
b3u-2.0.0.dist-info/METADATA
b3u-2.0.0.dist-info/WHEEL
b3u-2.0.0.dist-info/top_level.txt
b3u-2.0.0.dist-info/RECORD
