Metadata-Version: 2.1
Name: b3u
Version: 2.0.0
Summary: Utility for extracting Boto3 configuration information and method parameters from AWS resource URIs.
Home-page: https://github.com/nthparty/b3u
Author: Andrei Lapets
Author-email: a@lapets.io
License: MIT
Project-URL: Bug Tracker, https://github.com/nthparty/b3u/issues
Platform: any
Classifier: Programming Language :: Python :: 3
Classifier: Programming Language :: Python :: 3.7
Classifier: Programming Language :: Python :: 3.8
Classifier: Programming Language :: Python :: 3.9
Classifier: Programming Language :: Python :: 3.10
Classifier: License :: OSI Approved :: MIT License
Classifier: Operating System :: OS Independent
Requires-Python: >=3.7
License-File: LICENSE
